quant1024/__init__.py
quant1024/core.py
quant1024/exceptions.py
quant1024/auth/__init__.py
quant1024/auth/hmac_auth.py
quant1024/data/__init__.py
quant1024/data/dataset.py
quant1024/data/retriever.py
quant1024/data/adapters/__init__.py
quant1024/data/adapters/base_adapter.py
quant1024/data/adapters/blockchain_adapter.py
quant1024/data/adapters/exchange_adapter.py
quant1024/data/adapters/finance_adapter.py
quant1024/exchanges/__init__.py
quant1024/exchanges/base.py
quant1024/exchanges/exchange_1024ex.py
quant1024/models/__init__.py
quant1024/models/account.py
quant1024/models/market.py
quant1024/models/order.py
quant1024/utils/__init__.py
quant1024/utils/helpers.py
quant1024-0.3.0.dist-info/METADATA
quant1024-0.3.0.dist-info/WHEEL
quant1024-0.3.0.dist-info/licenses/LICENSE
quant1024-0.3.0.dist-info/RECORD
