Metadata-Version: 2.4
Name: quant1024
Version: 0.3.0
Summary: Multi-source quantitative trading toolkit for structured data retrieval and real-time trading - supports exchanges, financial data providers, and blockchain sources
Project-URL: Homepage, https://github.com/chuci-qin/quant1024
Project-URL: Repository, https://github.com/chuci-qin/quant1024
Project-URL: Documentation, https://github.com/chuci-qin/quant1024
Project-URL: Issues, https://github.com/chuci-qin/quant1024/issues
Author-email: 1024 Exchange <1024exchange@gmail.com>
License:                                  Apache License
License-File: LICENSE
Keywords: algorithmic-trading,backtest,data-retrieval,finance,multi-source,quant,quantitative,strategy,trading
Classifier: Development Status :: 4 - Beta
Classifier: Intended Audience :: Developers
Classifier: Intended Audience :: Financial and Insurance Industry
Classifier: License :: OSI Approved :: Apache Software License
Classifier: Programming Language :: Python :: 3
Classifier: Programming Language :: Python :: 3.8
Classifier: Programming Language :: Python :: 3.9
Classifier: Programming Language :: Python :: 3.10
Classifier: Programming Language :: Python :: 3.11
Classifier: Programming Language :: Python :: 3.12
Classifier: Topic :: Office/Business :: Financial
Classifier: Topic :: Scientific/Engineering
Classifier: Topic :: Software Development :: Libraries :: Python Modules
Requires-Python: >=3.8
Requires-Dist: numpy>=1.24.0
Requires-Dist: pandas>=2.0.0
Requires-Dist: pydantic>=2.0.0
Requires-Dist: requests>=2.31.0
Provides-Extra: all
Requires-Dist: web3>=6.0.0; extra == 'all'
Requires-Dist: yfinance>=0.2.0; extra == 'all'
Provides-Extra: blockchain
Requires-Dist: web3>=6.0.0; extra == 'blockchain'
Provides-Extra: dev
Requires-Dist: pytest-cov>=4.1.0; extra == 'dev'
Requires-Dist: pytest>=7.4.0; extra == 'dev'
Requires-Dist: responses>=0.23.0; extra == 'dev'
Requires-Dist: yfinance>=0.2.0; extra == 'dev'
Provides-Extra: yahoo
Requires-Dist: yfinance>=0.2.0; extra == 'yahoo'
